DatawhaleQianghuaXuexiZhongwenJiaocheng/README.md
DatawhaleQianghuaXuexiZhongwenJiaocheng/__init__.py
DatawhaleQianghuaXuexiZhongwenJiaocheng/__main__.py
DatawhaleQianghuaXuexiZhongwenJiaocheng/file.epub
DatawhaleQianghuaXuexiZhongwenJiaocheng/index.html
DatawhaleQianghuaXuexiZhongwenJiaocheng/css/__init__.py
DatawhaleQianghuaXuexiZhongwenJiaocheng/css/annotations.css
DatawhaleQianghuaXuexiZhongwenJiaocheng/css/main.css
DatawhaleQianghuaXuexiZhongwenJiaocheng/css/normalize.css
DatawhaleQianghuaXuexiZhongwenJiaocheng/css/popup.css
DatawhaleQianghuaXuexiZhongwenJiaocheng/font/__init__.py
DatawhaleQianghuaXuexiZhongwenJiaocheng/font/fontello.eot
DatawhaleQianghuaXuexiZhongwenJiaocheng/font/fontello.svg
DatawhaleQianghuaXuexiZhongwenJiaocheng/font/fontello.ttf
DatawhaleQianghuaXuexiZhongwenJiaocheng/font/fontello.woff
DatawhaleQianghuaXuexiZhongwenJiaocheng/img/__init__.py
DatawhaleQianghuaXuexiZhongwenJiaocheng/img/annotator-glyph-sprite.png
DatawhaleQianghuaXuexiZhongwenJiaocheng/img/annotator-icon-sprite.png
DatawhaleQianghuaXuexiZhongwenJiaocheng/img/apple-touch-icon.png
DatawhaleQianghuaXuexiZhongwenJiaocheng/img/cancelfullscreen.png
DatawhaleQianghuaXuexiZhongwenJiaocheng/img/close.png
DatawhaleQianghuaXuexiZhongwenJiaocheng/img/fullscreen.png
DatawhaleQianghuaXuexiZhongwenJiaocheng/img/loader.gif
DatawhaleQianghuaXuexiZhongwenJiaocheng/img/menu-icon.png
DatawhaleQianghuaXuexiZhongwenJiaocheng/img/save.png
DatawhaleQianghuaXuexiZhongwenJiaocheng/img/saved.png
DatawhaleQianghuaXuexiZhongwenJiaocheng/img/settings-s.png
DatawhaleQianghuaXuexiZhongwenJiaocheng/img/settings.png
DatawhaleQianghuaXuexiZhongwenJiaocheng/img/star.png
DatawhaleQianghuaXuexiZhongwenJiaocheng/js/__init__.py
DatawhaleQianghuaXuexiZhongwenJiaocheng/js/epub.js
DatawhaleQianghuaXuexiZhongwenJiaocheng/js/epub.min.js
DatawhaleQianghuaXuexiZhongwenJiaocheng/js/epub.min.map
DatawhaleQianghuaXuexiZhongwenJiaocheng/js/hooks.min.js
DatawhaleQianghuaXuexiZhongwenJiaocheng/js/hooks.min.map
datawhale_qianghua_xuexi_zhongwen_jiaocheng-2024.3.5.0.dist-info/METADATA
datawhale_qianghua_xuexi_zhongwen_jiaocheng-2024.3.5.0.dist-info/WHEEL
datawhale_qianghua_xuexi_zhongwen_jiaocheng-2024.3.5.0.dist-info/entry_points.txt
datawhale_qianghua_xuexi_zhongwen_jiaocheng-2024.3.5.0.dist-info/top_level.txt
datawhale_qianghua_xuexi_zhongwen_jiaocheng-2024.3.5.0.dist-info/RECORD
